KuaiShouGetCnString.py
__init__.py
setup.py
KuaiShouGetCnString.egg-info/PKG-INFO
KuaiShouGetCnString.egg-info/SOURCES.txt
KuaiShouGetCnString.egg-info/dependency_links.txt
KuaiShouGetCnString.egg-info/top_level.txt