Metadata-Version: 1.0
Name: KuaiShouGetCnString
Version: 0.1.2
Summary: A font processing function 
Home-page: https://github.com/jinmingzhou/KuaiShouGetCnString
Author: robin
Author-email: 1983273232@qq.com
License: MIT Licence
Keywords: pip,KuaiShouGetCnString
Platform: any
